gpmmatch/__init__.py
gpmmatch/correct.py
gpmmatch/default.py
gpmmatch/gpmmatch.py
gpmmatch/io.py
gpmmatch-1.5.4.dist-info/licenses/LICENSE
gpmmatch-1.5.4.dist-info/METADATA
gpmmatch-1.5.4.dist-info/WHEEL
gpmmatch-1.5.4.dist-info/top_level.txt
gpmmatch-1.5.4.dist-info/RECORD
