Metadata-Version: 2.4
Name: gpmmatch
Version: 1.5.4
Summary: Volume matching of ground radar and GPM satellite data.
Author-email: Valentin Louf <valentin.louf@bom.gov.au>
License: Apache-2.0
Project-URL: Documentation, https://github.com/vlouf/gpmmatch#readme
Project-URL: Source, https://github.com/vlouf/gpmmatch
Project-URL: Tracker, https://github.com/vlouf/gpmmatch/issues
Classifier: Development Status :: 5 - Production/Stable
Classifier: Intended Audience :: Developers
Classifier: Intended Audience :: Education
Classifier: Intended Audience :: Science/Research
Classifier: License :: OSI Approved :: Apache Software License
Classifier: Programming Language :: Python :: 3.9
Classifier: Programming Language :: Python :: 3.10
Classifier: Programming Language :: Python :: 3.11
Classifier: Programming Language :: Python :: 3.12
Classifier: Programming Language :: Python :: 3.13
Classifier: Topic :: Scientific/Engineering :: Atmospheric Science
Requires-Python: >=3.9
License-File: LICENSE
Requires-Dist: numpy
Requires-Dist: scipy
Requires-Dist: pandas
Requires-Dist: h5py
Requires-Dist: netCDF4
Requires-Dist: xarray
Requires-Dist: pyodim
Requires-Dist: pyproj
Dynamic: license-file
